ttbo_hello/__init__.py
ttbo_hello/main.py
ttbo_hello-0.3.dist-info/METADATA
ttbo_hello-0.3.dist-info/WHEEL
ttbo_hello-0.3.dist-info/entry_points.txt
ttbo_hello-0.3.dist-info/top_level.txt
ttbo_hello-0.3.dist-info/RECORD
