Metadata-Version: 2.1
Name: ttbo_hello
Version: 0.3
Requires-Dist: click
